scap/__init__.py
scap-0.0.1.dist-info/LICENSE
scap-0.0.1.dist-info/METADATA
scap-0.0.1.dist-info/WHEEL
scap-0.0.1.dist-info/entry_points.txt
scap-0.0.1.dist-info/top_level.txt
scap-0.0.1.dist-info/RECORD
