Metadata-Version: 2.1
Name: scap
Version: 0.0.1
Summary: Package for scap server.
Home-page: https://github.com/stacknix/scap
Author: Ashish Sahu
Author-email: spiraldeveloper@gmail.com
License: MIT
Keywords: python package atom
Platform: UNKNOWN
Classifier: Programming Language :: Python :: 3
Classifier: License :: OSI Approved :: MIT License
Classifier: Operating System :: OS Independent
License-File: LICENSE
